ssdpy/__init__.py
ssdpy/client.py
ssdpy/compat.py
ssdpy/constants.py
ssdpy/http_helper.py
ssdpy/protocol.py
ssdpy/server.py
ssdpy/version.py
ssdpy/cli/__init__.py
ssdpy/cli/client.py
ssdpy/cli/server.py
ssdpy-0.4.1.dist-info/LICENSE
ssdpy-0.4.1.dist-info/METADATA
ssdpy-0.4.1.dist-info/WHEEL
ssdpy-0.4.1.dist-info/entry_points.txt
ssdpy-0.4.1.dist-info/top_level.txt
ssdpy-0.4.1.dist-info/RECORD
